wargame/__init__.py
wargame/abstractgameunit.py
wargame/attackoftheors.py
wargame/gameuniterror.py
wargame/gameutils.py
wargame/hut.py
wargame/knight.py
wargame/orcider.py
chys_private-2.0.1.dist-info/LICENSE.txt
chys_private-2.0.1.dist-info/METADATA
chys_private-2.0.1.dist-info/WHEEL
chys_private-2.0.1.dist-info/top_level.txt
chys_private-2.0.1.dist-info/RECORD
