Metadata-Version: 2.1
Name: chys-private
Version: 2.0.1
Summary: my private game
Home-page: http://localhost:8071/simple
Author: luoquan
Author-email: 178517202@qq.com
License: UNKNOWN
Platform: UNKNOWN
License-File: LICENSE.txt
